Metadata-Version: 2.1
Name: current-path
Version: 0.0.4
Summary: A small library for getting current path data for a script that imports this library.
Home-page: https://github.com/jon-edward/current_path
Author: jon-edward
Author-email: arithmatlic@gmail.com
License: UNKNOWN
Platform: UNKNOWN
Classifier: Operating System :: OS Independent
Classifier: Intended Audience :: Developers
Classifier: Programming Language :: Python :: 3.6
Classifier: Programming Language :: Python :: 3.7
Classifier: Programming Language :: Python :: 3.8
Classifier: Programming Language :: Python :: 3.9
Classifier: Programming Language :: Python :: 3.10
Classifier: Programming Language :: Python :: 3.11
Classifier: Programming Language :: Python :: Implementation :: CPython
Classifier: Programming Language :: Python :: Implementation :: PyPy
Classifier: License :: CC0 1.0 Universal (CC0 1.0) Public Domain Dedication
Requires-Python: >=3.6
License-File: LICENSE
